solace_stream_source/__init__.py
solace_stream_source/solace_queue_stream_reader.py
solace_stream_source/solace_stream_datasource.py
solace_streaming_connector/__init__.py
solace_spark_streaming_connector-0.4.0.dist-info/METADATA
solace_spark_streaming_connector-0.4.0.dist-info/WHEEL
solace_spark_streaming_connector-0.4.0.dist-info/top_level.txt
solace_spark_streaming_connector-0.4.0.dist-info/RECORD
