Metadata-Version: 2.1
Name: solace-spark-streaming-connector
Version: 0.4.0
Summary: spark structured streaming connector utility for solace pubsub queue.
Author-email: Indranil Tarafdar <indranil.tarafdar@databricks.com>
Requires-Dist: solace-pubsubplus ==1.9.0
Requires-Dist: requests ==2.28.1
